{
	"class" : {
		"open" : "bak 4/27/2016 13:52",
		"openForError:debugger:" : "bak 4/27/2016 14:02",
		"runDebugged:" : "bak 6/29/2016 15:43" },
	"instance" : {
		"activationChildren:" : "bak 5/12/2016 18:10",
		"activationDefinition" : "bak 1/9/2017 10:48",
		"activationHasChildren:" : "bak 5/12/2016 18:10",
		"activationIcon:" : "bak 4/28/2016 10:03",
		"activationLabel:" : "bak 4/28/2016 10:04",
		"activationMenu:" : "bak 1/5/2017 13:33",
		"activationSelection" : "bak 6/25/2016 17:15",
		"activations" : "bak 5/12/2016 15:09",
		"buildDataInspectorWith:in:" : "bak 1/9/2017 16:47",
		"buildLeftRightEditorsWith:in:" : "bak 1/5/2017 15:24",
		"buildWith:" : "bak 1/6/2017 14:28",
		"bytesViewer" : "bak 6/29/2016 15:12",
		"cViewer" : "bak 6/29/2016 15:48",
		"cogitViewer" : "bak 6/29/2016 15:18",
		"contextPart" : "bak 1/9/2017 18:23",
		"debugger" : "bak 4/27/2016 14:01",
		"debugger:" : "bak 4/27/2016 14:01",
		"doCompareActivation" : "bak 1/5/2017 20:23",
		"doDebugActivation" : "bak 1/4/2017 14:33",
		"doInto" : "bak 1/9/2017 18:02",
		"doOver" : "bak 1/6/2017 14:14",
		"doOverAndInspectActivation" : "bak 1/5/2017 13:32",
		"doProceed" : "bak 5/11/2016 23:30",
		"doProceedComparing" : "bak 1/9/2017 18:50",
		"doRestart" : "bak 6/25/2016 15:09",
		"doubleEditorViewer" : "bak 6/29/2016 15:17",
		"inspectActivation" : "bak 4/28/2016 10:57",
		"inspectLevel" : "bak 4/28/2016 11:03",
		"label:" : "bak 4/27/2016 19:46",
		"leftActivationDefinition" : "bak 6/29/2016 15:39",
		"leftActivationDefinitionSelection" : "bak 1/5/2017 12:14",
		"levelIcon:" : "bak 4/27/2016 19:38",
		"levelMenu:" : "bak 4/28/2016 11:03",
		"levelRepo" : "bak 4/27/2016 19:49",
		"levels" : "bak 4/27/2016 19:49",
		"maySelectActivation:" : "bak 6/29/2016 15:32",
		"selectedActivation" : "bak 5/12/2016 15:08",
		"selectedActivation:" : "bak 1/9/2017 17:40",
		"selectedActivations" : "bak 5/12/2016 15:11",
		"selectedLevel" : "bak 4/27/2016 19:44",
		"selectedLevel:" : "bak 5/12/2016 15:06",
		"setViewer:" : "bak 6/29/2016 15:26",
		"signaledError" : "bak 4/27/2016 14:02",
		"signaledError:" : "bak 4/27/2016 14:02",
		"singleEditorViewer" : "bak 6/29/2016 15:15",
		"smalltalkViewer" : "bak 6/29/2016 15:26",
		"stack" : "bak 4/29/2016 18:38",
		"updateActivations" : "bak 1/9/2017 11:21",
		"updateSelectedActivation" : "bak 1/5/2017 15:08",
		"updateSelectedActivations" : "bak 5/12/2016 15:07",
		"variables" : "bak 1/9/2017 17:34",
		"verifier" : "bak 1/5/2017 20:22",
		"verifyBeforeStepping" : "bak 1/9/2017 19:15" } }
